model_agnostic_toolkit/__init__.py
model_agnostic_toolkit/analyzer.py
model_agnostic_toolkit/model.py
model_agnostic_toolkit/types.py
model_agnostic_toolkit/datasets/__init__.py
model_agnostic_toolkit/datasets/classification_datasets.py
model_agnostic_toolkit/datasets/dataset.py
model_agnostic_toolkit/datasets/development_datasets.py
model_agnostic_toolkit/datasets/interaction_datasets.py
model_agnostic_toolkit/datasets/multiclassification_datasets.py
model_agnostic_toolkit/datasets/multiplication_datasets.py
model_agnostic_toolkit/datasets/preloaded_dataset.py
model_agnostic_toolkit/datasets/regression_datasets.py
model_agnostic_toolkit/plots/__init__.py
model_agnostic_toolkit/plots/ale_plots.py
model_agnostic_toolkit/plots/importance_plots.py
model_agnostic_toolkit/plots/interaction_plots.py
model_agnostic_toolkit/plots/model_plots.py
model_agnostic_toolkit/plots/pdp_plots.py
model_agnostic_toolkit/plots/pfi_plots.py
model_agnostic_toolkit/plots/shap_plots.py
model_agnostic_toolkit/plots/utils.py
model_agnostic_toolkit/tools/__init__.py
model_agnostic_toolkit/tools/tool.py
model_agnostic_toolkit/tools/utils.py
model_agnostic_toolkit/tools/GlobalSensitivityAnalysis/__init__.py
model_agnostic_toolkit/tools/GlobalSensitivityAnalysis/dsa.py
model_agnostic_toolkit/tools/GlobalSensitivityAnalysis/dsa_calc_utils.py
model_agnostic_toolkit/tools/GlobalSensitivityAnalysis/dsa_utils.py
model_agnostic_toolkit/tools/GlobalSensitivityAnalysis/utils.py
model_agnostic_toolkit/tools/ale/__init__.py
model_agnostic_toolkit/tools/ale/ale_importance.py
model_agnostic_toolkit/tools/ale/ale_interaction.py
model_agnostic_toolkit/tools/h_statistic/__init__.py
model_agnostic_toolkit/tools/h_statistic/h_statistic_interaction.py
model_agnostic_toolkit/tools/pdp/__init__.py
model_agnostic_toolkit/tools/pdp/pdp_importance.py
model_agnostic_toolkit/tools/pdp/pdp_interaction.py
model_agnostic_toolkit/tools/pfi/__init__.py
model_agnostic_toolkit/tools/pfi/pfi_importance.py
model_agnostic_toolkit-1.0.0.dist-info/METADATA
model_agnostic_toolkit-1.0.0.dist-info/WHEEL
model_agnostic_toolkit-1.0.0.dist-info/licenses/LICENSE.md
model_agnostic_toolkit-1.0.0.dist-info/RECORD
